module_for_install/__init__.py
module_for_install/decrement.py
module_for_install/increment.py
module_for_install/some_JSON_file.json
module_for_install-0.0.5.dist-info/METADATA
module_for_install-0.0.5.dist-info/WHEEL
module_for_install-0.0.5.dist-info/top_level.txt
module_for_install-0.0.5.dist-info/RECORD
