Metadata-Version: 2.1
Name: module-for-install
Version: 0.0.5
Summary: My Package for university task
Home-page: UNKNOWN
Author: Pavel Khomenko
Author-email: your@domain.com
License: UNKNOWN
Platform: UNKNOWN
